[{"difficulty":2,"timer":3000,"Progress":{"completionTime":1000,"cluesUsed":2,"achievements":[{"title":"lkhalhjg","unlocked":true},{"title":"utyuiyoiuo","unlocked":false}],"puzzlesSolved":[{"Puzzle":{"solution":"solution1","isSolved":true,"hints":["hint1","hint2","hint3"],"description":"puzzle1"},"String":"puzzle1"},{"Puzzle":{"solution":"solution2","isSolved":false,"hints":["hint1","hint2","hint3"],"description":"puzzle2"},"String":"puzzle2"}]},"leaderboard":{"players":[{"Integer":1,"User":{"currentRoom":"ID: d8b9e9e2-e9a3-4b49-818a-976c61288ae4\nMap: com.escape.code.Map@4f2410ac\nLeaderboard: Player Info: \nUsername: name\nPassword: passwordVolume: 10\nDifficulty: 3\nID: d8b9e9e2-e9a3-4b49-818a-976c61288ae4\nID: e0d413f5-1bcf-4cdc-b90f-f051b35ba5bb\nCurrent ID: d8b9e9e2-e9a3-4b49-818a-976c61288ae4\nPlayer Info: \nUsername: nam\nPassword: passVolume: 10\nDifficulty: 3\nID: d8b9e9e2-e9a3-4b49-818a-976c61288ae4\nID: e0d413f5-1bcf-4cdc-b90f-f051b35ba5bb\nCurrent ID: d8b9e9e2-e9a3-4b49-818a-976c61288ae4\n\nTimer: 3000\nDifficulty: 2\nProgress:\nID:\nClues Used: 2Completion Time: 1000\nAchievements:\nTitle: lkhalhjg\nUnlocked: true\/nTitle: utyuiyoiuo\nUnlocked: false\/nKey: puzzle1 Value: Description: puzzle1\nSolution: solution1\nSolved: true\nHints:\nhint1\nhint2\nhint3\nKey: puzzle2 Value: Description: puzzle2\nSolution: solution2\nSolved: false\nHints:\nhint1\nhint2\nhint3\n\nPuzzles:\nDescription: logic puzzle\nSolution: solution\nSolved: true\nHints:\nhint 1\nhint 2\nhint 3\n\nDescription: math puzzle\nSolution: solution\nSolved: false\nHints:\nhint 1\nhint 2\nhint 3\n\n","settings":{"volume":10,"difficulty":3},"password":"password","rooms":["d8b9e9e2-e9a3-4b49-818a-976c61288ae4","e0d413f5-1bcf-4cdc-b90f-f051b35ba5bb"],"username":"name"}},{"Integer":3,"User":{"currentRoom":"ID: d8b9e9e2-e9a3-4b49-818a-976c61288ae4\nMap: com.escape.code.Map@4f2410ac\nLeaderboard: Player Info: \nUsername: name\nPassword: passwordVolume: 10\nDifficulty: 3\nID: d8b9e9e2-e9a3-4b49-818a-976c61288ae4\nID: e0d413f5-1bcf-4cdc-b90f-f051b35ba5bb\nCurrent ID: d8b9e9e2-e9a3-4b49-818a-976c61288ae4\nPlayer Info: \nUsername: nam\nPassword: passVolume: 10\nDifficulty: 3\nID: d8b9e9e2-e9a3-4b49-818a-976c61288ae4\nID: e0d413f5-1bcf-4cdc-b90f-f051b35ba5bb\nCurrent ID: d8b9e9e2-e9a3-4b49-818a-976c61288ae4\n\nTimer: 3000\nDifficulty: 2\nProgress:\nID:\nClues Used: 2Completion Time: 1000\nAchievements:\nTitle: lkhalhjg\nUnlocked: true\/nTitle: utyuiyoiuo\nUnlocked: false\/nKey: puzzle1 Value: Description: puzzle1\nSolution: solution1\nSolved: true\nHints:\nhint1\nhint2\nhint3\nKey: puzzle2 Value: Description: puzzle2\nSolution: solution2\nSolved: false\nHints:\nhint1\nhint2\nhint3\n\nPuzzles:\nDescription: logic puzzle\nSolution: solution\nSolved: true\nHints:\nhint 1\nhint 2\nhint 3\n\nDescription: math puzzle\nSolution: solution\nSolved: false\nHints:\nhint 1\nhint 2\nhint 3\n\n","settings":{"volume":10,"difficulty":3},"password":"pass","rooms":["d8b9e9e2-e9a3-4b49-818a-976c61288ae4","e0d413f5-1bcf-4cdc-b90f-f051b35ba5bb"],"username":"nam"}}]},"puzzles":[{"solution":"solution","isSolved":true,"hints":["hint 1","hint 2","hint 3"],"description":"logic puzzle"},{"solution":"solution","isSolved":false,"hints":["hint 1","hint 2","hint 3"],"description":"math puzzle"}],"progressList":[{"Progress":{"completionTime":1000,"cluesUsed":2,"achievements":[{"title":"lkhalhjg","unlocked":true},{"title":"utyuiyoiuo","unlocked":false}],"puzzlesSolved":[{"Puzzle":{"solution":"solution1","isSolved":true,"hints":["hint1","hint2","hint3"],"description":"puzzle1"},"String":"puzzle1"},{"Puzzle":{"solution":"solution2","isSolved":false,"hints":["hint1","hint2","hint3"],"description":"puzzle2"},"String":"puzzle2"}]},"String":"name"},{"Progress":{"completionTime":1000,"cluesUsed":2,"achievements":[{"title":"lkhalhjg","unlocked":true},{"title":"utyuiyoiuo","unlocked":false}],"puzzlesSolved":[{"Puzzle":{"solution":"solution1","isSolved":true,"hints":["hint1","hint2","hint3"],"description":"puzzle1"},"String":"puzzle1"},{"Puzzle":{"solution":"solution2","isSolved":false,"hints":["hint1","hint2","hint3"],"description":"puzzle2"},"String":"puzzle2"}]},"String":"nam"}],"id":"d8b9e9e2-e9a3-4b49-818a-976c61288ae4","map":{"length":500,"mapName":"map","height":500}},{"difficulty":3,"timer":2000,"Progress":{"completionTime":1000,"cluesUsed":2,"achievements":[{"title":"lkhalhjg","unlocked":true},{"title":"utyuiyoiuo","unlocked":false}],"puzzlesSolved":[{"Puzzle":{"solution":"solution1","isSolved":true,"hints":["hint1","hint2","hint3"],"description":"puzzle1"},"String":"puzzle1"},{"Puzzle":{"solution":"solution2","isSolved":false,"hints":["hint1","hint2","hint3"],"description":"puzzle2"},"String":"puzzle2"}]},"leaderboard":{"players":[{"Integer":1,"User":{"currentRoom":"ID: e0d413f5-1bcf-4cdc-b90f-f051b35ba5bb\nMap: com.escape.code.Map@36aa7bc2\nLeaderboard: Player Info: \nUsername: name\nPassword: passwordVolume: 10\nDifficulty: 3\nID: d8b9e9e2-e9a3-4b49-818a-976c61288ae4\nID: e0d413f5-1bcf-4cdc-b90f-f051b35ba5bb\nCurrent ID: e0d413f5-1bcf-4cdc-b90f-f051b35ba5bb\nPlayer Info: \nUsername: nam\nPassword: passVolume: 10\nDifficulty: 3\nID: d8b9e9e2-e9a3-4b49-818a-976c61288ae4\nID: e0d413f5-1bcf-4cdc-b90f-f051b35ba5bb\nCurrent ID: e0d413f5-1bcf-4cdc-b90f-f051b35ba5bb\n\nTimer: 2000\nDifficulty: 3\nProgress:\nID:\nClues Used: 2Completion Time: 1000\nAchievements:\nTitle: lkhalhjg\nUnlocked: true\/nTitle: utyuiyoiuo\nUnlocked: false\/nKey: puzzle1 Value: Description: puzzle1\nSolution: solution1\nSolved: true\nHints:\nhint1\nhint2\nhint3\nKey: puzzle2 Value: Description: puzzle2\nSolution: solution2\nSolved: false\nHints:\nhint1\nhint2\nhint3\n\nPuzzles:\nDescription: logic puzzle\nSolution: solution\nSolved: true\nHints:\nhint 1\nhint 2\nhint 3\n\nDescription: math puzzle\nSolution: solution\nSolved: false\nHints:\nhint 1\nhint 2\nhint 3\n\n","settings":{"volume":10,"difficulty":3},"password":"password","rooms":["d8b9e9e2-e9a3-4b49-818a-976c61288ae4","e0d413f5-1bcf-4cdc-b90f-f051b35ba5bb"],"username":"name"}},{"Integer":3,"User":{"currentRoom":"ID: e0d413f5-1bcf-4cdc-b90f-f051b35ba5bb\nMap: com.escape.code.Map@36aa7bc2\nLeaderboard: Player Info: \nUsername: name\nPassword: passwordVolume: 10\nDifficulty: 3\nID: d8b9e9e2-e9a3-4b49-818a-976c61288ae4\nID: e0d413f5-1bcf-4cdc-b90f-f051b35ba5bb\nCurrent ID: e0d413f5-1bcf-4cdc-b90f-f051b35ba5bb\nPlayer Info: \nUsername: nam\nPassword: passVolume: 10\nDifficulty: 3\nID: d8b9e9e2-e9a3-4b49-818a-976c61288ae4\nID: e0d413f5-1bcf-4cdc-b90f-f051b35ba5bb\nCurrent ID: e0d413f5-1bcf-4cdc-b90f-f051b35ba5bb\n\nTimer: 2000\nDifficulty: 3\nProgress:\nID:\nClues Used: 2Completion Time: 1000\nAchievements:\nTitle: lkhalhjg\nUnlocked: true\/nTitle: utyuiyoiuo\nUnlocked: false\/nKey: puzzle1 Value: Description: puzzle1\nSolution: solution1\nSolved: true\nHints:\nhint1\nhint2\nhint3\nKey: puzzle2 Value: Description: puzzle2\nSolution: solution2\nSolved: false\nHints:\nhint1\nhint2\nhint3\n\nPuzzles:\nDescription: logic puzzle\nSolution: solution\nSolved: true\nHints:\nhint 1\nhint 2\nhint 3\n\nDescription: math puzzle\nSolution: solution\nSolved: false\nHints:\nhint 1\nhint 2\nhint 3\n\n","settings":{"volume":10,"difficulty":3},"password":"pass","rooms":["d8b9e9e2-e9a3-4b49-818a-976c61288ae4","e0d413f5-1bcf-4cdc-b90f-f051b35ba5bb"],"username":"nam"}}]},"puzzles":[{"solution":"solution","isSolved":true,"hints":["hint 1","hint 2","hint 3"],"description":"logic puzzle"},{"solution":"solution","isSolved":false,"hints":["hint 1","hint 2","hint 3"],"description":"math puzzle"}],"progressList":[{"Progress":{"completionTime":1000,"cluesUsed":2,"achievements":[{"title":"lkhalhjg","unlocked":true},{"title":"utyuiyoiuo","unlocked":false}],"puzzlesSolved":[{"Puzzle":{"solution":"solution1","isSolved":true,"hints":["hint1","hint2","hint3"],"description":"puzzle1"},"String":"puzzle1"},{"Puzzle":{"solution":"solution2","isSolved":false,"hints":["hint1","hint2","hint3"],"description":"puzzle2"},"String":"puzzle2"}]},"String":"name"},{"Progress":{"completionTime":1000,"cluesUsed":2,"achievements":[{"title":"lkhalhjg","unlocked":true},{"title":"utyuiyoiuo","unlocked":false}],"puzzlesSolved":[{"Puzzle":{"solution":"solution1","isSolved":true,"hints":["hint1","hint2","hint3"],"description":"puzzle1"},"String":"puzzle1"},{"Puzzle":{"solution":"solution2","isSolved":false,"hints":["hint1","hint2","hint3"],"description":"puzzle2"},"String":"puzzle2"}]},"String":"nam"}],"id":"e0d413f5-1bcf-4cdc-b90f-f051b35ba5bb","map":{"length":800,"mapName":"special map","height":1200}}]